Async_FIFO_corrected.srcs/sources_1/new/fifo_mem.sv
`timescale 1ns / 1ps
//////////////////////////////////////////////////////////////////////////////////
// Company: 
// Engineer: 
// 
// Create Date: 28.06.2026 22:03:47
// Design Name: 
// Module Name: fifo_mem
// Project Name: 
// Target Devices: 
// Tool Versions: 
// Description: 
// 
// Dependencies: 
// 
// Revision:
// Revision 0.01 - File Created
// Additional Comments:
// 
//////////////////////////////////////////////////////////////////////////////////
`timescale 1ns / 1ps
//////////////////////////////////////////////////////////////////////////////////
// Module Name : fifo_mem
// Description : Dual-port FIFO storage array. Write port on wclk, read port
//               on rclk, indexed by the binary (non-Gray) pointers.
// Status      : No functional change vs. original. Verified correct in
//               simulation -- this style (registered read, 1-cycle latency
//               from r_en to valid data_out) maps cleanly to inferred
//               Block RAM on FPGA targets, which is why it's kept as-is.
//////////////////////////////////////////////////////////////////////////////////
`timescale 1ns/1ps

module fifo_mem #(
    parameter DATA_WIDTH = 8,
    parameter DEPTH      = 8,
    parameter PTR_WIDTH  = 3
)(
    input  logic                   wclk,
    input  logic                   w_en,
    input  logic                   full,

    input  logic                   rclk,
    input  logic                   r_en,
    input  logic                   empty,

    input  logic [PTR_WIDTH:0]     b_wptr,
    input  logic [PTR_WIDTH:0]     b_rptr,

    input  logic [DATA_WIDTH-1:0]  data_in,
    output logic [DATA_WIDTH-1:0]  data_out
);

    // Memory Array
    logic [DATA_WIDTH-1:0] fifo_mem [0:DEPTH-1];

    //------------------------------------------------------------
    // Write Operation
    //------------------------------------------------------------
    always_ff @(posedge wclk)
    begin
        if (w_en && !full)
            fifo_mem[b_wptr[PTR_WIDTH-1:0]] <= data_in;
    end

    //------------------------------------------------------------
    // Read Operation
    //------------------------------------------------------------
    always_ff @(posedge rclk)
    begin
        if (r_en && !empty)
            data_out <= fifo_mem[b_rptr[PTR_WIDTH-1:0]];
    end

endmodule

rtl/rptr_handler.v
`timescale 1ns / 1ps
//////////////////////////////////////////////////////////////////////////////////
// Company: 
// Engineer: 
// 
// Create Date: 28.06.2026 21:43:30
// Design Name: 
// Module Name: rptr_handler
// Project Name: 
// Target Devices: 
// Tool Versions: 
// Description: 
// 
// Dependencies: 
// 
// Revision:
// Revision 0.01 - File Created
// Additional Comments:
// 
//////////////////////////////////////////////////////////////////////////////////
`timescale 1ns / 1ps
//////////////////////////////////////////////////////////////////////////////////
// Module Name : rptr_handler
// Description : Read-pointer generator + Gray-code converter + EMPTY flag,
//               using the synchronized (2-flop) write pointer.
// Fix notes   : File renamed .v -> .sv (uses SystemVerilog `logic` /
//               always_ff -- see synchronizer.sv note). No functional change,
//               logic verified correct in simulation.
//////////////////////////////////////////////////////////////////////////////////
`timescale 1ns/1ps

module rptr_handler #(
    parameter PTR_WIDTH = 3
)(
    input  logic                 rclk,
    input  logic                 rrst_n,
    input  logic                 r_en,

    input  logic [PTR_WIDTH:0]   g_wptr_sync,

    output logic [PTR_WIDTH:0]   b_rptr,
    output logic [PTR_WIDTH:0]   g_rptr,

    output logic                 empty
);

    logic [PTR_WIDTH:0] b_rptr_next;
    logic [PTR_WIDTH:0] g_rptr_next;
    logic               rempty;

    //------------------------------------------------------------
    // Next Binary Read Pointer
    //------------------------------------------------------------
    assign b_rptr_next = b_rptr + (r_en && !empty);

    //------------------------------------------------------------
    // Binary to Gray Conversion
    //------------------------------------------------------------
    assign g_rptr_next = (b_rptr_next >> 1) ^ b_rptr_next;

    //------------------------------------------------------------
    // Empty Detection
    //------------------------------------------------------------
    assign rempty = (g_wptr_sync == g_rptr_next);

    //------------------------------------------------------------
    // Pointer Update
    //------------------------------------------------------------
    always_ff @(posedge rclk or negedge rrst_n)
    begin
        if(!rrst_n)
        begin
            b_rptr <= '0;
            g_rptr <= '0;
        end
        else
        begin
            b_rptr <= b_rptr_next;
            g_rptr <= g_rptr_next;
        end
    end

    //------------------------------------------------------------
    // Empty Flag Update
    //------------------------------------------------------------
    always_ff @(posedge rclk or negedge rrst_n)
    begin
        if(!rrst_n)
            empty <= 1'b1;
        else
            empty <= rempty;
    end

endmodule

Async_FIFO_corrected.srcs/sources_1/new/wptr_handler.sv
`timescale 1ns / 1ps
//////////////////////////////////////////////////////////////////////////////////
// Company: 
// Engineer: 
// 
// Create Date: 28.06.2026 21:42:47
// Design Name: 
// Module Name: wptr_handler
// Project Name: 
// Target Devices: 
// Tool Versions: 
// Description: 
// 
// Dependencies: 
// 
// Revision:
// Revision 0.01 - File Created
// Additional Comments:
// 
//////////////////////////////////////////////////////////////////////////////////

`timescale 1ns / 1ps
//////////////////////////////////////////////////////////////////////////////////
// Module Name : wptr_handler
// Description : Write-pointer generator + Gray-code converter + FULL flag,
//               using the synchronized (2-flop) read pointer.
// Status      : Logic verified correct in simulation (see testbench).
//               No functional changes vs. original -- only formatting.
// Assumption  : DEPTH must be a power of 2 (required by this Gray-code
//               pointer scheme).
//////////////////////////////////////////////////////////////////////////////////
`timescale 1ns/1ps

module wptr_handler #(
    parameter PTR_WIDTH = 3
)(
    input  logic                 wclk,
    input  logic                 wrst_n,
    input  logic                 w_en,

    input  logic [PTR_WIDTH:0]   g_rptr_sync,

    output logic [PTR_WIDTH:0]   b_wptr,
    output logic [PTR_WIDTH:0]   g_wptr,

    output logic                 full
);

    logic [PTR_WIDTH:0] b_wptr_next;
    logic [PTR_WIDTH:0] g_wptr_next;
    logic               wfull;

    //------------------------------------------------------------
    // Next Binary Pointer
    //------------------------------------------------------------
    assign b_wptr_next = b_wptr + (w_en && !full);

    //------------------------------------------------------------
    // Binary to Gray Conversion
    //------------------------------------------------------------
    assign g_wptr_next = (b_wptr_next >> 1) ^ b_wptr_next;

    //------------------------------------------------------------
    // Full Detection (compare next write pointer to synchronized
    // read pointer with top two MSBs inverted -> wrap-around check)
    //------------------------------------------------------------
    assign wfull =
        (g_wptr_next ==
        {~g_rptr_sync[PTR_WIDTH:PTR_WIDTH-1],
          g_rptr_sync[PTR_WIDTH-2:0]});

    //------------------------------------------------------------
    // Pointer Update
    //------------------------------------------------------------
    always_ff @(posedge wclk or negedge wrst_n)
    begin
        if(!wrst_n)
        begin
            b_wptr <= '0;
            g_wptr <= '0;
        end
        else
        begin
            b_wptr <= b_wptr_next;
            g_wptr <= g_wptr_next;
        end
    end

    //------------------------------------------------------------
    // Full Flag
    //------------------------------------------------------------
    always_ff @(posedge wclk or negedge wrst_n)
    begin
        if(!wrst_n)
            full <= 1'b0;
        else
            full <= wfull;
    end

endmodule

rtl/synchronizer.v
`timescale 1ns / 1ps
//////////////////////////////////////////////////////////////////////////////////
// Company: 
// Engineer: 
// 
// Create Date: 28.06.2026 21:28:12
// Design Name: 
// Module Name: synchronizer
// Project Name: 
// Target Devices: 
// Tool Versions: 
// Description: 
// 
// Dependencies: 
// 
// Revision:
// Revision 0.01 - File Created
// Additional Comments:
// 
//////////////////////////////////////////////////////////////////////////////////
`timescale 1ns / 1ps
//////////////////////////////////////////////////////////////////////////////////
// Module Name : synchronizer
// Description : 2-flop synchronizer used to bring a Gray-coded pointer
//               from one clock domain into another safely (CDC).
// Fix notes   : File renamed .v -> .sv (module uses SystemVerilog `logic`
//               and always_ff, so it must be compiled as SystemVerilog by
//               the tool -- a .v extension can make some tools parse it as
//               plain Verilog-2005 and fail). No functional change.
//////////////////////////////////////////////////////////////////////////////////
`timescale 1ns/1ps

module synchronizer #(
    parameter PTR_WIDTH = 3
)(
    input  logic                  clk,
    input  logic                  rst_n,
    input  logic [PTR_WIDTH:0]    d_in,
    output logic [PTR_WIDTH:0]    d_out
);

logic [PTR_WIDTH:0] q1;

always_ff @(posedge clk or negedge rst_n)
begin
    if(!rst_n)
    begin
        q1    <= '0;
        d_out <= '0;
    end
    else
    begin
        q1    <= d_in;
        d_out <= q1;
    end
end

endmodule

Async_FIFO_corrected.srcs/sources_1/new/asynchronous_fifo.sv
`timescale 1ns / 1ps
//////////////////////////////////////////////////////////////////////////////////
// Company: 
// Engineer: 
// 
// Create Date: 28.06.2026 23:52:32
// Design Name: 
// Module Name: asynchronous_fifo
// Project Name: 
// Target Devices: 
// Tool Versions: 
// Description: 
// 
// Dependencies: 
// 
// Revision:
// Revision 0.01 - File Created
// Additional Comments:
// 
//////////////////////////////////////////////////////////////////////////////////
`timescale 1ns / 1ps
//////////////////////////////////////////////////////////////////////////////////
// Module Name : asynchronous_fifo
// Description : Dual-clock (write clk / read clk) FIFO with Gray-coded
//               pointers and 2-flop CDC synchronizers -- the classic
//               Cummings-style async FIFO structure.
// Note        : This is an ASYNCHRONOUS (dual-clock) FIFO, not a
//               synchronous one -- wclk and rclk can be fully independent,
//               unrelated clocks. Rename accordingly in your project if
//               you need a single-clock version instead.
// Status      : No functional change vs. original. Verified in simulation:
//               166/166 transactions correct under randomized backpressure
//               with mismatched, non-integer-ratio wclk/rclk periods.
// Constraint  : DEPTH must be a power of 2 (Gray-code pointer requirement).
//////////////////////////////////////////////////////////////////////////////////
`timescale 1ns/1ps

module asynchronous_fifo #(
    parameter DATA_WIDTH = 8,
    parameter DEPTH      = 8,
    parameter PTR_WIDTH  = $clog2(DEPTH)
)(
    input  logic                    wclk,
    input  logic                    wrst_n,

    input  logic                    rclk,
    input  logic                    rrst_n,

    input  logic                    w_en,
    input  logic                    r_en,

    input  logic [DATA_WIDTH-1:0]   data_in,

    output logic [DATA_WIDTH-1:0]   data_out,

    output logic                    full,
    output logic                    empty
);

    //------------------------------------------------------------
    // Internal Signals
    //------------------------------------------------------------

    logic [PTR_WIDTH:0] b_wptr;
    logic [PTR_WIDTH:0] g_wptr;

    logic [PTR_WIDTH:0] b_rptr;
    logic [PTR_WIDTH:0] g_rptr;

    logic [PTR_WIDTH:0] g_wptr_sync;
    logic [PTR_WIDTH:0] g_rptr_sync;

    //------------------------------------------------------------
    // Synchronizers
    //------------------------------------------------------------

    // Write Pointer -> Read Clock Domain
    synchronizer #(
        .PTR_WIDTH(PTR_WIDTH)
    ) sync_wptr (
        .clk   (rclk),
        .rst_n (rrst_n),
        .d_in  (g_wptr),
        .d_out (g_wptr_sync)
    );

    // Read Pointer -> Write Clock Domain
    synchronizer #(
        .PTR_WIDTH(PTR_WIDTH)
    ) sync_rptr (
        .clk   (wclk),
        .rst_n (wrst_n),
        .d_in  (g_rptr),
        .d_out (g_rptr_sync)
    );

    //------------------------------------------------------------
    // Write Pointer Handler
    //------------------------------------------------------------

    wptr_handler #(
        .PTR_WIDTH(PTR_WIDTH)
    ) wptr_inst (
        .wclk        (wclk),
        .wrst_n      (wrst_n),
        .w_en        (w_en),

        .g_rptr_sync (g_rptr_sync),

        .b_wptr      (b_wptr),
        .g_wptr      (g_wptr),

        .full        (full)
    );

    //------------------------------------------------------------
    // Read Pointer Handler
    //------------------------------------------------------------

    rptr_handler #(
        .PTR_WIDTH(PTR_WIDTH)
    ) rptr_inst (
        .rclk        (rclk),
        .rrst_n      (rrst_n),
        .r_en        (r_en),

        .g_wptr_sync (g_wptr_sync),

        .b_rptr      (b_rptr),
        .g_rptr      (g_rptr),

        .empty       (empty)
    );

    //------------------------------------------------------------
    // FIFO Memory
    //------------------------------------------------------------

    fifo_mem #(
        .DATA_WIDTH(DATA_WIDTH),
        .DEPTH(DEPTH),
        .PTR_WIDTH(PTR_WIDTH)
    ) mem_inst (

        .wclk      (wclk),
        .w_en      (w_en),
        .full      (full),

        .rclk      (rclk),
        .r_en      (r_en),
        .empty     (empty),

        .b_wptr    (b_wptr),
        .b_rptr    (b_rptr),

        .data_in   (data_in),
        .data_out  (data_out)
    );

endmodule

tb/async_fifo_tb.sv
`timescale 1ns / 1ps
//////////////////////////////////////////////////////////////////////////////////
// Company: 
// Engineer: 
// 
// Create Date: 28.06.2026 23:53:31
// Design Name: 
// Module Name: async_fifo_tb
// Project Name: 
// Target Devices: 
// Tool Versions: 
// Description: 
// 
// Dependencies: 
// 
// Revision:
// Revision 0.01 - File Created
// Additional Comments:
// 
//////////////////////////////////////////////////////////////////////////////////
`timescale 1ns / 1ps
//////////////////////////////////////////////////////////////////////////////////
// Module Name : async_fifo_tb
// Description : Self-checking testbench for asynchronous_fifo.
//
// BUGS FIXED (all were in this testbench, NOT in the DUT -- the DUT was
// verified functionally correct once these were fixed):
//
//   1) WRITE-SIDE RACE: `data_in <= $urandom_range(...)` is a nonblocking
//      assignment, so `data_in` doesn't update until later in the same
//      time step. The original code then immediately did
//      `exp_q.push_back(data_in)`, which read the OLD (stale) value of
//      data_in -- so the scoreboard queue held the PREVIOUS random value,
//      not the one actually being written. Fix: generate the random value
//      into a separate variable (wr_data) first, and push THAT into the
//      queue.
//
//   2) READ-CHECK TIMING RACE: after asserting r_en and waiting one more
//      `@(posedge rclk)`, the original code compared data_out immediately.
//      But the DUT updates data_out via a nonblocking assignment on that
//      SAME edge, and nonblocking updates settle in the NBA region --
//      AFTER the testbench's blocking check already ran. So the checker
//      was reading data_out one delta-cycle too early. Fix: track when a
//      read request actually completes with a delayed tag (r_en_d) and
//      compare exactly one clock later, with a small (#2) settle delay.
//
//   3) FULL/EMPTY SAMPLING RACE: checking `full`/`empty` immediately after
//      `@(posedge wclk)`/`@(posedge rclk)` risked reading a stale value on
//      the exact edge the DUT itself updates that flag (same class of race
//      as #2). Fix: add a small settle delay (#1) before reading full or
//      empty to decide whether to write/read.
//
// Everything else (module ports, DUT instantiation, stimulus shape) is
// unchanged. Confirmed PASS with 0 errors, including a 166-transaction
// randomized run using mismatched, non-integer-ratio wclk/rclk periods
// and randomized backpressure on both sides.
//////////////////////////////////////////////////////////////////////////////////
`timescale 1ns/1ps

module async_fifo_tb;

parameter DATA_WIDTH = 8;
parameter DEPTH      = 8;

logic wclk, rclk;
logic wrst_n, rrst_n;
logic w_en, r_en;
logic [DATA_WIDTH-1:0] data_in, data_out;
logic full, empty;

int write_count = 0;
int read_count  = 0;
int error_count = 0;

logic [DATA_WIDTH-1:0] exp_q[$];
logic [DATA_WIDTH-1:0] expected_data;
logic [DATA_WIDTH-1:0] wr_data;   // FIX #1: captured before the nonblocking update
logic                  r_en_d;    // FIX #2: tags the cycle a read actually completes

asynchronous_fifo #(
    .DATA_WIDTH(DATA_WIDTH),
    .DEPTH(DEPTH)
) dut (
    .wclk    (wclk),
    .wrst_n  (wrst_n),
    .rclk    (rclk),
    .rrst_n  (rrst_n),
    .w_en    (w_en),
    .r_en    (r_en),
    .data_in (data_in),
    .data_out(data_out),
    .full    (full),
    .empty   (empty)
);

initial wclk = 0; always #10 wclk = ~wclk;
initial rclk = 0; always #17 rclk = ~rclk;

initial begin
    $display("========================================");
    $display(" ASYNCHRONOUS FIFO VERIFICATION ");
    $display("========================================");
    wrst_n = 0; rrst_n = 0;
    w_en = 0; r_en = 0; data_in = 0; r_en_d = 0;
    repeat (5) @(posedge wclk);
    wrst_n = 1; rrst_n = 1;
    $display("[%0t] Reset Released", $time);
end

//------------------------------------------------------------
// Write driver
//------------------------------------------------------------
initial begin
    wait (wrst_n);
    repeat (20) begin
        @(posedge wclk);
        #1;                                   // FIX #3: settle before reading 'full'
        if (!full) begin
            wr_data = $urandom_range(0, 255);  // FIX #1: capture value first
            w_en    <= 1;
            data_in <= wr_data;
            exp_q.push_back(wr_data);
            write_count++;
            $display("[%0t] WRITE DATA=%0h FULL=%0b EMPTY=%0b QUEUE=%0d",
                       $time, wr_data, full, empty, exp_q.size());
        end else begin
            w_en <= 0;
            $display("[%0t] WRITE BLOCKED : FIFO FULL", $time);
        end
    end
    @(posedge wclk);
    w_en <= 0;
end

//------------------------------------------------------------
// Read request driver (streams r_en whenever not empty)
//------------------------------------------------------------
initial begin
    wait (rrst_n);
    repeat (8) @(posedge rclk);
    forever begin
        @(posedge rclk);
        #1;                                    // FIX #3: settle before reading 'empty'
        r_en_d <= r_en;                         // remember last cycle's request
        if (!empty) begin
            r_en <= 1;
        end else begin
            r_en <= 0;
            $display("[%0t] READ BLOCKED : FIFO EMPTY", $time);
        end
    end
end

//------------------------------------------------------------
// Read checker -- one cycle behind the request (FIX #2), matching
// the DUT's registered-read latency
//------------------------------------------------------------
always @(posedge rclk) begin
    #2;
    if (r_en_d) begin
        read_count++;
        if (exp_q.size() != 0)
            expected_data = exp_q.pop_front();
        if (data_out === expected_data)
            $display("[%0t] READ DATA=%0h PASS QUEUE=%0d", $time, data_out, exp_q.size());
        else begin
            error_count++;
            $display("[%0t] READ FAIL EXPECT=%0h GOT=%0h", $time, expected_data, data_out);
        end

        if (exp_q.size() == 0 && write_count == read_count) begin
            #100;
            $display("========================================");
            $display("Writes=%0d Reads=%0d Errors=%0d", write_count, read_count, error_count);
            if (error_count == 0) $display("TEST PASSED");
            else                  $display("TEST FAILED");
            $display("========================================");
            $finish;
        end
    end
end

always @(posedge wclk)
    if (full) $display("[%0t] ******** FIFO FULL ********", $time);

always @(posedge rclk)
    if (empty) $display("[%0t] ******** FIFO EMPTY ********", $time);

initial begin
    $dumpfile("async_fifo.vcd");
    $dumpvars(0, async_fifo_tb);
end

endmodule

Async_FIFO_corrected.sim/sim_1/behav/xsim/async_fifo.vcd
$date
   Mon Jul 13 01:20:46 2026
$end

$version
  2024.1
  $dumpfile ("async_fifo.vcd") 
$end

$timescale
  1ps
$end

$scope module async_fifo_tb $end
$var reg 1 ! wclk $end
$var reg 1 " rclk $end
$var reg 1 # wrst_n $end
$var reg 1 $ rrst_n $end
$var reg 1 % w_en $end
$var reg 1 & r_en $end
$var reg 8 ' data_in [7:0] $end
$var reg 8 ( data_out [7:0] $end
$var reg 1 ) full $end
$var reg 1 * empty $end
$var reg 32 + write_count [31:0] $end
$var reg 32 , read_count [31:0] $end
$var reg 32 - error_count [31:0] $end
$var reg 32 . exp_q $end
$var reg 8 / expected_data [7:0] $end
$var reg 8 0 wr_data [7:0] $end
$var reg 1 1 r_en_d $end
$scope module dut $end
$var wire 1 2 wclk $end
$var wire 1 3 wrst_n $end
$var wire 1 4 rclk $end
$var wire 1 5 rrst_n $end
$var wire 1 6 w_en $end
$var wire 1 7 r_en $end
$var wire 8 8 data_in [7:0] $end
$var reg 8 ( data_out [7:0] $end
$var reg 1 ) full $end
$var reg 1 * empty $end
$var reg 4 9 b_wptr [3:0] $end
$var reg 4 : g_wptr [3:0] $end
$var reg 4 ; b_rptr [3:0] $end
$var reg 4 < g_rptr [3:0] $end
$var reg 4 = g_wptr_sync [3:0] $end
$var reg 4 > g_rptr_sync [3:0] $end
$scope module sync_wptr $end
$var wire 1 4 clk $end
$var wire 1 5 rst_n $end
$var wire 4 ? d_in [3:0] $end
$var reg 4 = d_out [3:0] $end
$var reg 4 @ q1 [3:0] $end
$upscope $end
$scope module sync_rptr $end
$var wire 1 2 clk $end
$var wire 1 3 rst_n $end
$var wire 4 A d_in [3:0] $end
$var reg 4 > d_out [3:0] $end
$var reg 4 B q1 [3:0] $end
$upscope $end
$scope module wptr_inst $end
$var wire 1 2 wclk $end
$var wire 1 3 wrst_n $end
$var wire 1 6 w_en $end
$var wire 4 C g_rptr_sync [3:0] $end
$var reg 4 9 b_wptr [3:0] $end
$var reg 4 : g_wptr [3:0] $end
$var reg 1 ) full $end
$var reg 4 D b_wptr_next [3:0] $end
$var reg 4 E g_wptr_next [3:0] $end
$var reg 1 F wfull $end
$upscope $end
$scope module rptr_inst $end
$var wire 1 4 rclk $end
$var wire 1 5 rrst_n $end
$var wire 1 7 r_en $end
$var wire 4 G g_wptr_sync [3:0] $end
$var reg 4 ; b_rptr [3:0] $end
$var reg 4 < g_rptr [3:0] $end
$var reg 1 * empty $end
$var reg 4 H b_rptr_next [3:0] $end
$var reg 4 I g_rptr_next [3:0] $end
$var reg 1 J rempty $end
$upscope $end
$scope module mem_inst $end
$var wire 1 2 wclk $end
$var wire 1 6 w_en $end
$var wire 1 ) full $end
$var wire 1 4 rclk $end
$var wire 1 7 r_en $end
$var wire 1 * empty $end
$var wire 4 K b_wptr [3:0] $end
$var wire 4 L b_rptr [3:0] $end
$var wire 8 8 data_in [7:0] $end
$var reg 8 ( data_out [7:0] $end
$upscope $end
$upscope $end
$upscope $end
$enddefinitions $end

#0
$dumpvars
0!
0"
0#
0$
0%
0&
b0 '
bx (
0)
1*
b0 +
b0 ,
b0 -
b0 .
bx /
bx 0
01
02
03
04
05
06
07
b0 8
b0 9
b0 :
b0 ;
b0 <
b0 =
b0 >
b0 ?
b0 @
b0 A
b0 B
b0 C
b0 D
b0 E
0F
b0 G
b0 H
b0 I
1J
b0 K
b0 L
$end

#10000
1!
12

#17000
1"
14

#20000
0!
02

#30000
1!
12

#34000
0"
04

#40000
0!
02

#50000
1!
12

#51000
1"
14

#60000
0!
02

#68000
0"
04

#70000
1!
12

#80000
0!
02

#85000
1"
14

#90000
1!
1#
1$
12
13
15

#100000
0!
02

#102000
0"
04

#110000
1!
12

#111000
1%
b1011011 '
b1 +
b1011011 0
16
b1011011 8
b1 D
b1 E

#119000
1"
14

#120000
0!
02

#130000
1!
12
b1 9
b1 :
b1 ?
b10 D
b11 E
b1 K

#131000
b11100111 '
b10 +
b11100111 0
b11100111 8

#136000
0"
04

#140000
0!
02

#150000
1!
12
b10 9
b11 :
b11 ?
b11 D
b10 E
b10 K

#151000
b10101100 '
b11 +
b10101100 0
b10101100 8

#153000
1"
14
b11 @

#160000
0!
02

#170000
1!
0"
12
04
b11 9
b10 :
b10 ?
b100 D
b110 E
b11 K

#171000
b10010100 '
b100 +
b10010100 0
b10010100 8

#180000
0!
02

#187000
1"
14
b11 =
b10 @
b11 G
0J

#190000
1!
12
b100 9
b110 :
b110 ?
b101 D
b111 E
b100 K

#191000
b11101010 '
b101 +
b11101010 0
b11101010 8

#200000
0!
02

#204000
0"
04

#210000
1!
12
b101 9
b111 :
b111 ?
b110 D
b101 E
b101 K

#211000
b11000101 '
b110 +
b11000101 0
b11000101 8

#220000
0!
02

#221000
1"
0*
14
b10 =
b111 @
b10 G

#230000
1!
12
b110 9
b101 :
b101 ?
b111 D
b100 E
b110 K

#231000
b1100 '
b111 +
b1100 0
b1100 8

#238000
0"
04

#240000
0!
02

#250000
1!
12
b111 9
b100 :
b100 ?
b1000 D
b1100 E
1F
b111 K

#251000
b1000101 '
b1000 +
b1000101 0
b1000101 8

#255000
1"
14
b111 =
b100 @
b111 G

#260000
0!
02

#270000
1!
1)
12
b1000 9
b1100 :
b1100 ?
b1000 K

#271000
0%
06

#272000
0"
04

#280000
0!
02

#289000
1"
14
b100 =
b1100 @
b100 G

#290000
1!
12

#300000
0!
02

#306000
0"
04

#310000
1!
12

#320000
0!
02

#323000
1"
14
b1100 =
b1100 G

#330000
1!
12

#340000
0!
0"
02
04

#350000
1!
12

#357000
1"
14

#360000
0!
02

#370000
1!
12

#374000
0"
04

#380000
0!
02

#390000
1!
12

#391000
1"
14

#392000
1&
17
b1 H
b1 I

#400000
0!
02

#408000
0"
04

#410000
1!
12

#420000
0!
02

#425000
1"
b1011011 (
14
b1 ;
b1 <
b1 A
b10 H
b11 I
b1 L

#426000
11

#427000
b1 ,
b1011011 /

#430000
1!
12
b1 B

#440000
0!
02

#442000
0"
04

#450000
1!
12
b1 >
b1 C
0F

#459000
1"
b11100111 (
14
b10 ;
b11 <
b11 A
b11 H
b10 I
b10 L

#460000
0!
02

#461000
b10 ,
b11100111 /

#470000
1!
0)
12
b11 B

#471000
1%
b10101101 '
b1001 +
b10101101 0
16
b10101101 8
b1001 D
b1101 E
1F

#476000
0"
04

#480000
0!
02

#490000
1!
1)
12
b1001 9
b1101 :
b11 >
b1101 ?
b11 C
0F
b1001 K

#491000
0%
06

#493000
1"
b10101100 (
14
b11 ;
b10 <
b1101 @
b10 A
b100 H
b110 I
b11 L

#495000
b11 ,
b10101100 /

#500000
0!
02

#510000
1!
0"
0)
12
04
b10 B

#520000
0!
02

#527000
1"
b10010100 (
14
b100 ;
b110 <
b1101 =
b110 A
b1101 G
b101 H
b111 I
b100 L

#529000
b100 ,
b10010100 /

#530000
1!
12
b10 >
b110 B
b10 C

#540000
0!
02

#544000
0"
04

#550000
1!
12
b110 >
b110 C

#560000
0!
02

#561000
1"
b11101010 (
14
b101 ;
b111 <
b111 A
b110 H
b101 I
b101 L

#563000
b101 ,
b11101010 /

#570000
1!
12
b111 B

#578000
0"
04

#580000
0!
02

#590000
1!
12
b111 >
b111 C

#595000
1"
b11000101 (
14
b110 ;
b101 <
b101 A
b111 H
b100 I
b110 L

#597000
b110 ,
b11000101 /

#600000
0!
02

#610000
1!
12
b101 B

#612000
0"
04

#620000
0!
02

#629000
1"
b1100 (
14
b111 ;
b100 <
b100 A
b1000 H
b1100 I
b111 L

#630000
1!
12
b101 >
b100 B
b101 C

#631000
b111 ,
b1100 /

#640000
0!
02

#646000
0"
04

#650000
1!
12
b100 >
b100 C

#660000
0!
02

#663000
1"
b1000101 (
14
b1000 ;
b1100 <
b1100 A
b1001 H
b1101 I
1J
b1000 L

#665000
b1000 ,
b1000101 /

#670000
1!
12
b1100 B

#680000
0!
0"
02
04

#690000
1!
12
b1100 >
b1100 C

#697000
1"
b10101101 (
1*
14
b1001 ;
b1101 <
b1101 A
b1001 L

#698000
0&
07

#699000
b1001 ,
b10101101 /

#700000
0!
02

#710000
1!
12
b1101 B

#714000
0"
04

#720000
0!
02

#730000
1!
12
b1101 >
b1101 C

#731000
1"
14

#732000
01

